bv/__init__.py
bv/config.py
bv/data.py
bv/default.py
bv/error.py
bv/io.py
bv/ui.py
bv/utils.py
bv/vdtui.py
bv/config/bed.cfg
bv/config/csv.cfg
bv/config/excel.cfg
bv/config/gff.cfg
bv/config/gtf.cfg
bv/config/maf.cfg
bv/config/tsv.cfg
bv/config/vcf.cfg
bv-0.1.4.dist-info/LICENSE
bv-0.1.4.dist-info/METADATA
bv-0.1.4.dist-info/WHEEL
bv-0.1.4.dist-info/entry_points.txt
bv-0.1.4.dist-info/top_level.txt
bv-0.1.4.dist-info/RECORD
